MANIFEST.in
README.md
setup.py
frojd_fabric/__init__.py
frojd_fabric/api.py
frojd_fabric/hooks.py
frojd_fabric/logger.py
frojd_fabric/paths.py
frojd_fabric.egg-info/PKG-INFO
frojd_fabric.egg-info/SOURCES.txt
frojd_fabric.egg-info/dependency_links.txt
frojd_fabric.egg-info/not-zip-safe
frojd_fabric.egg-info/requires.txt
frojd_fabric.egg-info/top_level.txt
frojd_fabric/ext/__init__.py
frojd_fabric/ext/celeryd.py
frojd_fabric/ext/composer.py
frojd_fabric/ext/envfile.py
frojd_fabric/ext/forever.py
frojd_fabric/ext/gunicorn.py
frojd_fabric/ext/mysql.py
frojd_fabric/ext/nginx.py
frojd_fabric/ext/npm.py
frojd_fabric/ext/uwsgi.py
frojd_fabric/ext/virtualenv.py
frojd_fabric/recipes/__init__.py
frojd_fabric/recipes/django.py
frojd_fabric/recipes/django_uwsgi.py
frojd_fabric/recipes/django_uwsgi_emperor.py
frojd_fabric/recipes/node.py
frojd_fabric/recipes/node_forever.py
frojd_fabric/recipes/wordpress.py
frojd_fabric/recipes/vendors/__init__.py
frojd_fabric/recipes/vendors/glesys_wordpress.py
frojd_fabric/transfer/__init__.py
frojd_fabric/transfer/git.py
frojd_fabric/utils/__init__.py
frojd_fabric/utils/elocal.py
frojd_fabric/utils/erun.py
requirements/install.txt
requirements/tests.txt