Metadata-Version: 1.1
Name: frojd-fabric
Version: 1.1.1
Summary: A simple to use deployment toolkit built on top of Fabric
Home-page: https://github.com/frojd/frojd-fabric
Author: Fröjd
Author-email: martin.sandstrom@frojd.se
License: MIT
Platform: UNKNOWN
Classifier: Development Status :: 4 - Beta
Classifier: Environment :: Console
Classifier: Environment :: Web Environment
Classifier: Intended Audience :: Developers
Classifier: Intended Audience :: System Administrators
Classifier: Natural Language :: English
Classifier: License :: OSI Approved :: MIT License
Classifier: Programming Language :: Python
Classifier: Programming Language :: Python :: 2
Classifier: Programming Language :: Python :: 2.7
Classifier: Topic :: Software Development :: Build Tools
Classifier: Topic :: Software Development :: Libraries
Classifier: Topic :: System :: Software Distribution
Classifier: Topic :: System :: Systems Administration
